ipdetector.py
ipdetector-0.1.dist-info/LICENSE
ipdetector-0.1.dist-info/METADATA
ipdetector-0.1.dist-info/WHEEL
ipdetector-0.1.dist-info/top_level.txt
ipdetector-0.1.dist-info/RECORD
