Metadata-Version: 2.1
Name: ipdetector
Version: 0.1
Summary: Detect whether the given input is Public IP/ Private IP/ Public IP range or Private IP range
Home-page: https://github.com/1uffyD9/ipdetector
Author: 1uffyD9
Author-email: mugiwara.luffyd9@gmail.com
License: UNKNOWN
Platform: UNKNOWN
Classifier: Programming Language :: Python :: 3
Classifier: Programming Language :: Python :: 3.7
Classifier: Operating System :: OS Independent
